mrepo/__init__.py
mrepo/process.py
mrepo-0.1.4.dist-info/entry_points.txt
mrepo-0.1.4.dist-info/WHEEL
mrepo-0.1.4.dist-info/METADATA
mrepo-0.1.4.dist-info/RECORD
